packageTest/__init__.py
packageTest/packageTest.py
pyaedt_lib/__init__.py
pyaedt_lib/desktop/__init__.py
pyaedt_lib/desktop/desktop.py
pyaedt_lib/pydesign/__init__.py
pyaedt_lib/pydesign/hfss.py
pyaedt_lib/pydesign/maxwell3d.py
pyaedt_lib/pydesktop/__init__.py
pyaedt_lib/pydesktop/desktop.py
pyaedt_lib/pymodeler/__init__.py
pyaedt_lib/pymodeler/modeler.py
pyaedt_lib/pymodeler/polyline.py
pyaedt_lib/pyproject/__init__.py
pyaedt_lib/pyproject/project.py
pyaedt_lib/variable/__init__.py
pyaedt_lib/variable/variable.py
pyaedt_lib-0.0.1.7.dist-info/METADATA
pyaedt_lib-0.0.1.7.dist-info/WHEEL
pyaedt_lib-0.0.1.7.dist-info/top_level.txt
pyaedt_lib-0.0.1.7.dist-info/RECORD
